sefef/__init__.py
sefef/evaluation.py
sefef/labeling.py
sefef/modelcard.py
sefef/postprocessing.py
sefef/scoring.py
sefef/visualization.py
sefef-3.0.0.dist-info/licenses/LICENSE
sefef-3.0.0.dist-info/METADATA
sefef-3.0.0.dist-info/WHEEL
sefef-3.0.0.dist-info/top_level.txt
sefef-3.0.0.dist-info/RECORD
